salpa_cppcore.cp313-win_amd64.pyd
salpa/LocalFit.cpp
salpa/LocalFit.h
salpa/__init__.py
salpa/fsalpa.py
salpa/msalpa.py
salpa/salpa_cppcore.cpp
salpa-1.0.dist-info/licenses/LICENSE
salpa-1.0.dist-info/METADATA
salpa-1.0.dist-info/WHEEL
salpa-1.0.dist-info/top_level.txt
salpa-1.0.dist-info/RECORD
