Metadata-Version: 2.4
Name: salpa
Version: 1.0
Summary: Artifact removal for multichannel electrophysiology
Author-email: "Daniel A. Wagenaar" <daw@caltech.edu>
License-Expression: GPL-3.0-or-later
Project-URL: Homepage, https://github.com/wagenadl/salpa
Classifier: Programming Language :: Python :: 3
Classifier: Programming Language :: C++
Classifier: Operating System :: POSIX :: Linux
Classifier: Operating System :: Microsoft :: Windows
Requires-Python: >=3.12
License-File: LICENSE
Requires-Dist: numpy
Dynamic: license-file
